banjara/__init__.py
banjara/dto/__init__.py
banjara/models/__init__.py
banjara/ui/__init__.py
banjara/ui/banjara.tcss
banjara/ui/overview.py
banjara-0.1.0.dist-info/METADATA
banjara-0.1.0.dist-info/WHEEL
banjara-0.1.0.dist-info/entry_points.txt
banjara-0.1.0.dist-info/RECORD
